<?xml version="1.0" encoding="UTF-8"?>

<zamowienia xmlns:xsi="http://www.w3.org/2001/XMLSchema-instance"
      xsi:noNamespaceSchemaLocation="xmlSchema.xsd">
	
	<naglowek>
        <przedmiot>Programowanie komunikacji człowiek-komputer</przedmiot>
        <opis>Zad 2. XML plus definicja XMLSchema</opis>
        <autorzy>
            <autor id='ID-1'>
                <imie>Kamil</imie>
                <nazwisko>Recheta</nazwisko>
                <album>205310</album>
            </autor>
            <autor id='ID-2'>
                <imie>Dominik</imie>
                <nazwisko>Dominiak</nazwisko>
                <album>204193</album>
            </autor>
        </autorzy>
    </naglowek>
      
    <zamowienie dostawa='kurier' faktura='tak'>
        <towary>
            <zamowione_towary list="e030 e031"/>
        </towary>
        <klient>
            <imie>Jan</imie>
            <nazwisko>Kowalski</nazwisko>
            <adres>
                <miasto>Piotrków Trybunalski</miasto>
                <ulica>Wronia</ulica>
                <nr_domu>50</nr_domu>
                <nr_lokalu>3</nr_lokalu>
                <kod>97-300</kod>
            </adres>
            <email>jan.kowalski@gmail.com</email>
            <telefon>614234767</telefon>
            <nip>725-18-01-126</nip>
        </klient>
        <data>
            <dzien>10</dzien>
            <miesiac>3</miesiac>
            <rok>2018</rok>
        </data>
        <koszt>2999.99</koszt>   
    </zamowienie>    
    
</zamowienia>
